pylom/__init__.py
pylom/lom.py
pylom/reader.py
pylom/writer.py
test/__init__.py
test/test_fail_reader_elements.py
test/test_fail_writer_elements.py
test/test_functions.py
test/test_reader_elements.py
test/test_writer_elements.py
pylom-1.6.3.dist-info/LICENSE
pylom-1.6.3.dist-info/METADATA
pylom-1.6.3.dist-info/WHEEL
pylom-1.6.3.dist-info/top_level.txt
pylom-1.6.3.dist-info/RECORD
