Metadata-Version: 2.1
Name: pylom
Version: 1.6.3
Summary: Library for parsing IMS-LOM xml records.
Home-page: https://github.com/kennisnet/pylom
Author: Wim Muskee
Author-email: w.muskee@kennisnet.nl
License: MIT
Keywords: lom parsing xml
Platform: UNKNOWN
Classifier: License :: OSI Approved :: MIT License
Classifier: Operating System :: OS Independent
Classifier: Programming Language :: Python :: 2.7
Classifier: Programming Language :: Python :: 3
Classifier: Topic :: Software Development :: Libraries
Classifier: Topic :: Text Processing :: Markup :: XML
Requires-Dist: lxml
Requires-Dist: vobject
